agentic_workflow/__init__.py
agentic_workflow/__main__.py
agentic_workflow/cli/CLI_ARCHITECTURE.md
agentic_workflow/cli/__init__.py
agentic_workflow/cli/display.py
agentic_workflow/cli/formatting.py
agentic_workflow/cli/main.py
agentic_workflow/cli/theme.py
agentic_workflow/cli/ui_utils.py
agentic_workflow/cli/commands/__init__.py
agentic_workflow/cli/commands/active_session.py
agentic_workflow/cli/commands/global_ops.py
agentic_workflow/cli/commands/project_ops.py
agentic_workflow/cli/handlers/__init__.py
agentic_workflow/cli/handlers/artifact_handlers.py
agentic_workflow/cli/handlers/entry_handlers.py
agentic_workflow/cli/handlers/global_handlers.py
agentic_workflow/cli/handlers/project_handlers.py
agentic_workflow/cli/handlers/query_handlers.py
agentic_workflow/cli/handlers/session_handlers.py
agentic_workflow/cli/handlers/workflow_handlers.py
agentic_workflow/cli/tui/TUI_ARCHITECTURE.md
agentic_workflow/cli/tui/__init__.py
agentic_workflow/cli/tui/branding.py
agentic_workflow/cli/tui/container.py
agentic_workflow/cli/tui/error_handler.py
agentic_workflow/cli/tui/exceptions.py
agentic_workflow/cli/tui/main.py
agentic_workflow/cli/tui/setup.py
agentic_workflow/cli/tui/types.py
agentic_workflow/cli/tui/actions/__init__.py
agentic_workflow/cli/tui/actions/base_action.py
agentic_workflow/cli/tui/actions/workflow_actions.py
agentic_workflow/cli/tui/controllers/__init__.py
agentic_workflow/cli/tui/controllers/agent_operations_controller.py
agentic_workflow/cli/tui/controllers/artifact_management_controller.py
agentic_workflow/cli/tui/controllers/base_controller.py
agentic_workflow/cli/tui/controllers/global_menu_controller.py
agentic_workflow/cli/tui/controllers/project_management_controller.py
agentic_workflow/cli/tui/controllers/project_menu_controller.py
agentic_workflow/cli/tui/controllers/project_navigation_controller.py
agentic_workflow/cli/tui/controllers/project_wizard_controller.py
agentic_workflow/cli/tui/controllers/system_info_controller.py
agentic_workstation-1.0.11.dist-info/METADATA
agentic_workstation-1.0.11.dist-info/WHEEL
agentic_workstation-1.0.11.dist-info/entry_points.txt
agentic_workstation-1.0.11.dist-info/RECORD
