Metadata-Version: 2.4
Name: agentic-workstation
Version: 1.0.11
Summary: Multi-agent planning and workflow orchestration system
Author-email: Sujith <sujith.eag@gmail.com>
License-Expression: MIT
Requires-Python: >=3.10
Requires-Dist: click>=8.1.0
Requires-Dist: jinja2>=3.1.0
Requires-Dist: jsonschema>=4.17.0
Requires-Dist: platformdirs>=3.0.0
Requires-Dist: pydantic>=2.0.0
Requires-Dist: pyyaml>=6.0.0
Requires-Dist: questionary>=2.0.0
Requires-Dist: rich-click>=1.7.0
Requires-Dist: rich>=13.0.0
Requires-Dist: structlog>=25.0.0
Requires-Dist: tomli>=1.2.0
Provides-Extra: auth
Requires-Dist: pyjwt>=2.8.0; extra == 'auth'
Provides-Extra: dev
Requires-Dist: mypy>=1.0.0; extra == 'dev'
Requires-Dist: pytest-cov>=4.0.0; extra == 'dev'
Requires-Dist: pytest>=7.0.0; extra == 'dev'
Requires-Dist: ruff>=0.1.0; extra == 'dev'
Provides-Extra: external
Requires-Dist: requests>=2.31.0; extra == 'external'
Provides-Extra: interactive
Requires-Dist: click-completion>=0.5.0; extra == 'interactive'
Provides-Extra: performance
Requires-Dist: cachetools>=5.3.0; extra == 'performance'
Provides-Extra: web
Requires-Dist: fastapi>=0.100.0; extra == 'web'
Requires-Dist: uvicorn>=0.23.0; extra == 'web'
